anyjsonthing/__init__.py
anyjsonthing/io.py
anyjsonthing/serializer.py
anyjsonthing/utils.py
anyjsonthing-0.4.0.dist-info/LICENSE
anyjsonthing-0.4.0.dist-info/METADATA
anyjsonthing-0.4.0.dist-info/WHEEL
anyjsonthing-0.4.0.dist-info/top_level.txt
anyjsonthing-0.4.0.dist-info/RECORD
