Metadata-Version: 2.1
Name: anyjsonthing
Version: 0.4.0
Summary: A library that implements serialization of simple data objects as JSON data.
Home-page: https://github.com/phohenecker/anyjsonthing
Author: Patrick Hohenecker
Author-email: patrick.hohenecker@gmx.at
License: Simplified BSD License
Classifier: Programming Language :: Python :: 3.9
Classifier: Programming Language :: Python :: 3.10
Classifier: Programming Language :: Python :: 3.11
Requires-Python: >=3.9
License-File: LICENSE
